nrl_test_data_generator/__init__.py
nrl_test_data_generator/cli.py
nrl_test_data_generator/generate_geojson_v2.py
nrl_test_data_generator/nrl_generator.py
nrl_test_data_generator-0.3.1.dist-info/METADATA
nrl_test_data_generator-0.3.1.dist-info/WHEEL
nrl_test_data_generator-0.3.1.dist-info/entry_points.txt
nrl_test_data_generator-0.3.1.dist-info/top_level.txt
nrl_test_data_generator-0.3.1.dist-info/RECORD
