Metadata-Version: 2.4
Name: nrl-test-data-generator
Version: 0.3.1
Summary: A utility for generating test data for the NRL (Nasjonalt Register over Luftfartshindre) project.
Project-URL: Homepage, https://github.com/3lbits/nrl-sdk
Project-URL: Documentation, https://3lbits.github.io/nrl-sdk/
Project-URL: Repository, https://github.com/3lbits/nrl-sdk.git
Project-URL: Issues, https://github.com/3lbits/nrl-sdk/issues
Requires-Python: >=3.13
Requires-Dist: anyio>=4.10.0
Requires-Dist: click>=8.2.1
Requires-Dist: nrl-sdk-lib>=0.1.23
Requires-Dist: xlsxwriter>=3.1.0
